watchmen_data_kernel/__init__.py
watchmen_data_kernel/cache/__init__.py
watchmen_data_kernel/cache/cache_manager.py
watchmen_data_kernel/cache/cache_service.py
watchmen_data_kernel/cache/data_source_cache.py
watchmen_data_kernel/cache/external_writer_cache.py
watchmen_data_kernel/cache/internal_cache.py
watchmen_data_kernel/cache/key_store_cache.py
watchmen_data_kernel/cache/pipeline_by_topic_cache.py
watchmen_data_kernel/cache/pipeline_cache.py
watchmen_data_kernel/cache/tenant_cache.py
watchmen_data_kernel/cache/topic_cache.py
watchmen_data_kernel/common/__init__.py
watchmen_data_kernel/common/exception.py
watchmen_data_kernel/common/settings.py
watchmen_data_kernel/encryption/__init__.py
watchmen_data_kernel/encryption/aes_encryptor.py
watchmen_data_kernel/encryption/center_masker.py
watchmen_data_kernel/encryption/date_masker.py
watchmen_data_kernel/encryption/encryptor.py
watchmen_data_kernel/encryption/encryptor_registry.py
watchmen_data_kernel/encryption/last_masker.py
watchmen_data_kernel/encryption/mail_masker.py
watchmen_data_kernel/encryption/md5_encryptor.py
watchmen_data_kernel/encryption/sha256_encryptor.py
watchmen_data_kernel/external_writer/__init__.py
watchmen_data_kernel/external_writer/external_writer_builder_registry.py
watchmen_data_kernel/external_writer/external_writer_registry.py
watchmen_data_kernel/meta/__init__.py
watchmen_data_kernel/meta/data_source_service.py
watchmen_data_kernel/meta/external_writer_service.py
watchmen_data_kernel/meta/key_store_service.py
watchmen_data_kernel/meta/pipeline_service.py
watchmen_data_kernel/meta/tenant_service.py
watchmen_data_kernel/meta/topic_service.py
watchmen_data_kernel/service/__init__.py
watchmen_data_kernel/service/service_helper.py
watchmen_data_kernel/service/storage_helper.py
watchmen_data_kernel/service/topic_structure_helper.py
watchmen_data_kernel/storage/__init__.py
watchmen_data_kernel/storage/data_entity_helper.py
watchmen_data_kernel/storage/data_service.py
watchmen_data_kernel-18.0.1.dist-info/METADATA
watchmen_data_kernel-18.0.1.dist-info/WHEEL
watchmen_data_kernel-18.0.1.dist-info/licenses/LICENSE
watchmen_data_kernel-18.0.1.dist-info/RECORD
